Day 2/design.sv
module day2(input p1a, input p1b, input p1c, input p1d, input p2a, input p2b, input p2c, input p2d, output p1y, output p2y);
  nand X1(p1y, p1a, p1b, p1c, p1d);
  nand X2(p2y, p2a, p2b, p2c, p2d );
endmodule

Day 2/testbench.sv
module testbench_day2;
  reg p1a, p1b, p1c, p1d, p2a, p2b, p2c, p2d;
  wire p1y, p2y;
  day2 uut (
    .p1a(p1a),
    .p1b(p1b),
    .p1c(p1c),
    .p1d(p1d),
    .p2a(p2a),
    .p2b(p2b),
    .p2c(p2c),
    .p2d(p2d),
    .p1y(p1y),
    .p2y(p2y)
  );
  
  initial
    begin
      $dumpvars(1, testbench_day2);
      p1a = 1'b0; p1b = 1'b0; p1c = 1'b0; p1d = 1'b0; p2a = 1'b0; p2b = 1'b0; p2c = 1'b0; p2d = 1'b0; #10;
      p1a = 1'b0; p1b = 1'b0; p1c = 1'b0; p1d = 1'b1; p2a = 1'b0; p2b = 1'b0; p2c = 1'b0; p2d = 1'b1; #10;
      p1a = 1'b0; p1b = 1'b0; p1c = 1'b1; p1d = 1'b0; p2a = 1'b0; p2b = 1'b0; p2c = 1'b1; p2d = 1'b0; #10;
      p1a = 1'b0; p1b = 1'b0; p1c = 1'b1; p1d = 1'b1; p2a = 1'b0; p2b = 1'b0; p2c = 1'b1; p2d = 1'b1; #10;
      p1a = 1'b0; p1b = 1'b1; p1c = 1'b0; p1d = 1'b0; p2a = 1'b0; p2b = 1'b1; p2c = 1'b0; p2d = 1'b0; #10;
      p1a = 1'b0; p1b = 1'b1; p1c = 1'b0; p1d = 1'b1; p2a = 1'b0; p2b = 1'b1; p2c = 1'b0; p2d = 1'b1; #10;
      p1a = 1'b0; p1b = 1'b1; p1c = 1'b1; p1d = 1'b0; p2a = 1'b0; p2b = 1'b1; p2c = 1'b1; p2d = 1'b0; #10;
      p1a = 1'b0; p1b = 1'b1; p1c = 1'b1; p1d = 1'b1; p2a = 1'b0; p2b = 1'b1; p2c = 1'b1; p2d = 1'b1; #10;
      p1a = 1'b1; p1b = 1'b1; p1c = 1'b0; p1d = 1'b0; p2a = 1'b1; p2b = 1'b1; p2c = 1'b0; p2d = 1'b0; #10;
      p1a = 1'b1; p1b = 1'b1; p1c = 1'b0; p1d = 1'b1; p2a = 1'b1; p2b = 1'b1; p2c = 1'b0; p2d = 1'b1; #10;
      p1a = 1'b1; p1b = 1'b1; p1c = 1'b1; p1d = 1'b0; p2a = 1'b1; p2b = 1'b1; p2c = 1'b1; p2d = 1'b0; #10;
      p1a = 1'b1; p1b = 1'b1; p1c = 1'b1; p1d = 1'b1; p2a = 1'b1; p2b = 1'b1; p2c = 1'b1; p2d = 1'b1; #10;
      $stop;
    end
endmodule

Day 2/verilog.vcd
$date
Sat Sep 30 10:47:33 2023
$end
$version
Riviera-PRO Version 2022.04.117.8517
$end
$timescale
1 ns
$end

$scope module testbench_day2 $end
$var wire 1 ! p1y $end
$var wire 1 " p2y $end
$var reg 1 # p1a $end
$var reg 1 $ p1b $end
$var reg 1 % p1c $end
$var reg 1 & p1d $end
$var reg 1 ' p2a $end
$var reg 1 ( p2b $end
$var reg 1 ) p2c $end
$var reg 1 * p2d $end
$upscope $end

$enddefinitions $end
$dumpvars
1!
1"
0#
0$
0%
0&
0'
0(
0)
0*
$end
#10
1&
1*
#20
1%
0&
1)
0*
#30
1&
1*
#40
1$
0%
0&
1(
0)
0*
#50
1&
1*
#60
1%
0&
1)
0*
#70
1&
1*
#80
1#
0%
0&
1'
0)
0*
#90
1&
1*
#100
1%
0&
1)
0*
#110
1&
1*
0!
0"
